ytcon/__init__.py
ytcon/__version__.py
ytcon/log.py
ytcon/yt.py
ytcon/app_update/bottom_widget_updater.py
ytcon/app_update/settings_section.py
ytcon/app_update/updater.py
ytcon/app_update/variables.py
ytcon/control/control.py
ytcon/control/exit.py
ytcon/control/variables.py
ytcon/downloader/hook.py
ytcon/downloader/main.py
ytcon/downloader/map_variables.py
ytcon/loops/error_printer.py
ytcon/loops/log_printer.py
ytcon/loops/render_tasks.py
ytcon/loops/tick_handlers.py
ytcon/misc/clipboard.py
ytcon/misc/ffmpeg.py
ytcon/render/colors.py
ytcon/render/loop.py
ytcon/render/progressbar_defs.py
ytcon/render/render.py
ytcon/render/static_methods.py
ytcon/settings/settings_processor.py
ytcon/settings_menu/render.py
ytcon/settings_menu/sections.py
ytcon/settings_menu/variables.py
ytcon/widgets/input_handler.py
ytcon/widgets/main_widgets.py
ytcon/widgets/top_pile.py
ytcon-0.6.2.dist-info/licenses/LICENSE
ytcon-0.6.2.dist-info/METADATA
ytcon-0.6.2.dist-info/WHEEL
ytcon-0.6.2.dist-info/entry_points.txt
ytcon-0.6.2.dist-info/top_level.txt
ytcon-0.6.2.dist-info/RECORD
