Metadata-Version: 2.4
Name: ytcon
Version: 0.6.2
Summary: yt-dlp pseudo-graphical console interface (TUI) ✨
Author-email: NikitaBeloglazov <nnikita.beloglazov@gmail.com>
License: MPL 2.0 License
Project-URL: Homepage, https://github.com/NikitaBeloglazov/ytcon
Project-URL: Bug Tracker, https://github.com/NikitaBeloglazov/ytcon/issues
Keywords: ytcon,yt-dlp,yt_dlp,ytdlp,tui
Classifier: Programming Language :: Python :: 3
Classifier: License :: OSI Approved :: Mozilla Public License 2.0 (MPL 2.0)
Classifier: Development Status :: 4 - Beta
Classifier: Environment :: Console :: Curses
Classifier: Topic :: Multimedia :: Video
Requires-Python: >=3.9
License-File: LICENSE
Requires-Dist: requests
Requires-Dist: urwid>=2.1.2
Requires-Dist: tqdm
Requires-Dist: clipman
Requires-Dist: ffmpeg-python>=0.2.0
Requires-Dist: yt_dlp
Dynamic: license-file
